yta_timer/__init__.py
yta_timer-0.0.7.dist-info/licenses/LICENSE
yta_timer-0.0.7.dist-info/METADATA
yta_timer-0.0.7.dist-info/WHEEL
yta_timer-0.0.7.dist-info/RECORD
