Metadata-Version: 2.4
Name: yta-timer
Version: 0.0.7
Summary: Youtube Autonomous Timer Module
License-File: LICENSE
Author: danialcala94
Author-email: danielalcalavalera@gmail.com
Requires-Python: ==3.9
Classifier: Programming Language :: Python :: 3
Classifier: Programming Language :: Python :: 3.9
